RBV_package/__init__.py
RBV_package/archive.py
RBV_package/config_package.py
RBV_package/data_extraction.py
RBV_package/dates.py
RBV_package/rbv_environment.py
rbv_package-2.0.0.dist-info/METADATA
rbv_package-2.0.0.dist-info/WHEEL
rbv_package-2.0.0.dist-info/top_level.txt
rbv_package-2.0.0.dist-info/RECORD
