Metadata-Version: 2.4
Name: rbv-package
Version: 2.0.0
Summary: Un package de fonction utiles pour la Vérification basée sur les risques
Author: Hubinont Jean-Philippe
Author-email: jphubinont@bluesquarehub.com
Dynamic: author
Dynamic: author-email
Dynamic: summary
